tutorhpa/__about__.py
tutorhpa/__init__.py
tutorhpa/plugin.py
tutorhpa/patches/.gitignore
tutorhpa/patches/k8s-override
tutorhpa/patches/kustomization-resources
tutorhpa/templates/hpa/k8s/hpa.yml
tutor_contrib_hpa-18.0.0.dist-info/METADATA
tutor_contrib_hpa-18.0.0.dist-info/WHEEL
tutor_contrib_hpa-18.0.0.dist-info/entry_points.txt
tutor_contrib_hpa-18.0.0.dist-info/top_level.txt
tutor_contrib_hpa-18.0.0.dist-info/RECORD
