Metadata-Version: 2.1
Name: tutor-contrib-hpa
Version: 18.0.0
Summary: Tutor plugin to enable HPA for Kubernetes installations of Open edX
Home-page: https://github.com/myusername/tutor-contrib-hpa
Author: Aulasneo
Author-email: andres@aulasneo.com
License: AGPLv3
Project-URL: Code, https://github.com/myusername/tutor-contrib-hpa
Project-URL: Issue tracker, https://github.com/myusername/tutor-contrib-hpa/issues
Classifier: Development Status :: 3 - Alpha
Classifier: Intended Audience :: Developers
Classifier: License :: OSI Approved :: GNU Affero General Public License v3
Classifier: Operating System :: OS Independent
Classifier: Programming Language :: Python
Classifier: Programming Language :: Python :: 3.7
Classifier: Programming Language :: Python :: 3.8
Classifier: Programming Language :: Python :: 3.9
Classifier: Programming Language :: Python :: 3.10
Requires-Python: >=3.7
Requires-Dist: tutor <19.0.0,>=18.0.0
